tls_syslog-0.2.0.dist-info/METADATA
tls_syslog-0.2.0.dist-info/RECORD
tls_syslog-0.2.0.dist-info/WHEEL
tls_syslog-0.2.0.dist-info/top_level.txt
tlssyslog/__init__.py
tlssyslog/handlers.py
tlssyslog/tests.py
tlssyslog/worker.py
