Metadata-Version: 2.1
Name: tls-syslog
Version: 0.2.0
Summary: Send syslog data over a TCP/TLS socket.
Home-page: https://gitlab.com/thelabnyc/python-tls-syslog
Author: Craig Weber
Author-email: crgwbr@gmail.com
License: ISC
Platform: UNKNOWN
Classifier: Development Status :: 5 - Production/Stable
Classifier: Environment :: Console
Classifier: Intended Audience :: Developers
Classifier: License :: OSI Approved :: ISC License (ISCL)
Classifier: Operating System :: Unix
Classifier: Operating System :: MacOS :: MacOS X
Classifier: Programming Language :: Python
Classifier: Programming Language :: Python :: 3
Classifier: Programming Language :: Python :: 3.5
Classifier: Programming Language :: Python :: 3.6
Classifier: Programming Language :: Python :: 3.7
Provides-Extra: sentry
Provides-Extra: development
Provides-Extra: development
Requires-Dist: flake8 (>=3.3.0); extra == 'development'
Requires-Dist: tox (>=2.7.0); extra == 'development'
Requires-Dist: versiontag (>=1.2.0); extra == 'development'
Provides-Extra: sentry
Requires-Dist: sentry-sdk (>=0.5.5); extra == 'sentry'
